booger/__init__.py
booger/cli.py
booger/discovery.py
booger/mcp_server.py
booger/process.py
booger/store.py
dev_booger-0.2.2.dist-info/METADATA
dev_booger-0.2.2.dist-info/WHEEL
dev_booger-0.2.2.dist-info/entry_points.txt
dev_booger-0.2.2.dist-info/licenses/LICENSE
dev_booger-0.2.2.dist-info/RECORD
