Metadata-Version: 2.4
Name: dev-booger
Version: 0.2.2
Summary: Multi-port log aggregator with MCP integration for Claude Code
Project-URL: Homepage, https://github.com/alfredosdpiii/dev-booger
Project-URL: Repository, https://github.com/alfredosdpiii/dev-booger
Project-URL: Issues, https://github.com/alfredosdpiii/dev-booger/issues
Author: alfredosdpiii
License: MIT
License-File: LICENSE
Classifier: Development Status :: 4 - Beta
Classifier: Environment :: Console
Classifier: Intended Audience :: Developers
Classifier: License :: OSI Approved :: MIT License
Classifier: Programming Language :: Python :: 3
Classifier: Programming Language :: Python :: 3.11
Classifier: Programming Language :: Python :: 3.12
Classifier: Programming Language :: Python :: 3.13
Classifier: Topic :: Software Development :: Build Tools
Classifier: Topic :: System :: Logging
Requires-Python: >=3.11
Requires-Dist: click>=8.1.0
Requires-Dist: fastmcp>=2.0.0
Requires-Dist: pyyaml>=6.0.0
Requires-Dist: rich>=13.0.0
